LogicPy/__init__.py
LogicPy/arithematic_circuit.py
LogicPy/combination_logic.py
LogicPy/conversion.py
LogicPy/counters.py
LogicPy/display_terminals.py
LogicPy/flipflops.py
LogicPy/gates.py
LogicPy/main_functions.py
LogicPy/shift_registers.py
LogicPy-0.0.1.dist-info/LICENSE.txt
LogicPy-0.0.1.dist-info/METADATA
LogicPy-0.0.1.dist-info/WHEEL
LogicPy-0.0.1.dist-info/top_level.txt
LogicPy-0.0.1.dist-info/RECORD
