Metadata-Version: 2.1
Name: LogicPy
Version: 0.0.1
Summary: Implementation of logic circuits using python
Home-page: https://github.com/Sunillad08/Digital_Logic
Author: Sunil Lad & Parth Khanolkar
Author-email: ladsunil08@gmail.com
License: MIT
Keywords: Logic circuit,pylogic
Platform: UNKNOWN
Classifier: Development Status :: 5 - Production/Stable
Classifier: Intended Audience :: Education
Classifier: Operating System :: Microsoft :: Windows :: Windows 10
Classifier: License :: OSI Approved :: MIT License
Classifier: Programming Language :: Python :: 3
